scaleout/__init__.py
scaleout/auth.py
scaleout/details.py
scaleout/errors.py
scaleout/project.py
scaleout/studioclient.py
scaleout/trackingclient.py
scaleout/version.py
scaleout/cli/__init__.py
scaleout/cli/create_cmd.py
scaleout/cli/default-project.tar.gz
scaleout/cli/delete_cmd.py
scaleout/cli/get_cmd.py
scaleout/cli/helpers.py
scaleout/cli/init_cmd.py
scaleout/cli/main.py
scaleout/cli/model_cmd.py
scaleout/cli/project_cmd.py
scaleout/cli/set_cmd.py
scaleout/cli/stackn_cmd.py
scaleout/cli/update_cmd.py
scaleout/config/__init__.py
scaleout/config/config.py
scaleout/repository/__init__.py
scaleout/repository/base.py
scaleout/repository/helpers.py
scaleout/repository/miniorepository.py
scaleout/repository/s3modelrepository.py
scaleout/runtime/__init__.py
scaleout/runtime/runtime.py
scaleout/utils/__init__.py
scaleout/utils/file.py
scaleout-0.1.0.dist-info/METADATA
scaleout-0.1.0.dist-info/WHEEL
scaleout-0.1.0.dist-info/entry_points.txt
scaleout-0.1.0.dist-info/top_level.txt
scaleout-0.1.0.dist-info/RECORD
